{
  "version": 0,
  "block": {
    "attributes": {
      "archive_size_bytes": {
        "type": "number",
        "description_kind": "plain",
        "computed": true
      },
      "creation_timestamp": {
        "type": "string",
        "description_kind": "plain",
        "computed": true
      },
      "description": {
        "type": "string",
        "description_kind": "plain",
        "computed": true
      },
      "disk_size_gb": {
        "type": "number",
        "description_kind": "plain",
        "computed": true
      },
      "family": {
        "type": "string",
        "description_kind": "plain",
        "optional": true,
        "computed": true
      },
      "filter": {
        "type": "string",
        "description_kind": "plain",
        "optional": true
      },
      "id": {
        "type": "string",
        "description_kind": "plain",
        "optional": true,
        "computed": true
      },
      "image_encryption_key_sha256": {
        "type": "string",
        "description_kind": "plain",
        "computed": true
      },
      "image_id": {
        "type": "string",
        "description_kind": "plain",
        "computed": true
      },
      "label_fingerprint": {
        "type": "string",
        "description_kind": "plain",
        "computed": true
      },
      "labels": {
        "type": [
          "map",
          "string"
        ],
        "description_kind": "plain",
        "computed": true
      },
      "licenses": {
        "type": [
          "list",
          "string"
        ],
        "description_kind": "plain",
        "computed": true
      },
      "most_recent": {
        "type": "bool",
        "description_kind": "plain",
        "optional": true
      },
      "name": {
        "type": "string",
        "description_kind": "plain",
        "optional": true,
        "computed": true
      },
      "project": {
        "type": "string",
        "description_kind": "plain",
        "optional": true,
        "computed": true
      },
      "self_link": {
        "type": "string",
        "description_kind": "plain",
        "computed": true
      },
      "source_disk": {
        "type": "string",
        "description_kind": "plain",
        "computed": true
      },
      "source_disk_encryption_key_sha256": {
        "type": "string",
        "description_kind": "plain",
        "computed": true
      },
      "source_disk_id": {
        "type": "string",
        "description_kind": "plain",
        "computed": true
      },
      "source_image_id": {
        "type": "string",
        "description_kind": "plain",
        "computed": true
      },
      "status": {
        "type": "string",
        "description_kind": "plain",
        "computed": true
      }
    },
    "description_kind": "plain"
  }
}