{
  "version": 0,
  "block": {
    "attributes": {
      "arn": {
        "type": "string",
        "description_kind": "plain",
        "computed": true
      },
      "certificate_arn": {
        "type": "string",
        "description_kind": "plain",
        "computed": true
      },
      "certificate_name": {
        "type": "string",
        "description_kind": "plain",
        "computed": true
      },
      "certificate_upload_date": {
        "type": "string",
        "description_kind": "plain",
        "computed": true
      },
      "cloudfront_domain_name": {
        "type": "string",
        "description_kind": "plain",
        "computed": true
      },
      "cloudfront_zone_id": {
        "type": "string",
        "description_kind": "plain",
        "computed": true
      },
      "domain_name": {
        "type": "string",
        "description_kind": "plain",
        "required": true
      },
      "domain_name_id": {
        "type": "string",
        "description_kind": "plain",
        "optional": true,
        "computed": true
      },
      "endpoint_configuration": {
        "type": [
          "list",
          [
            "object",
            {
              "ip_address_type": "string",
              "types": [
                "list",
                "string"
              ]
            }
          ]
        ],
        "description_kind": "plain",
        "computed": true
      },
      "id": {
        "type": "string",
        "description_kind": "plain",
        "optional": true,
        "computed": true
      },
      "policy": {
        "type": "string",
        "description_kind": "plain",
        "computed": true
      },
      "region": {
        "type": "string",
        "description": "Region where this resource will be [managed](https://docs.aws.amazon.com/general/latest/gr/rande.html#regional-endpoints). Defaults to the Region set in the [provider configuration](https://registry.terraform.io/providers/hashicorp/aws/latest/docs#aws-configuration-reference).",
        "description_kind": "plain",
        "optional": true,
        "computed": true
      },
      "regional_certificate_arn": {
        "type": "string",
        "description_kind": "plain",
        "computed": true
      },
      "regional_certificate_name": {
        "type": "string",
        "description_kind": "plain",
        "computed": true
      },
      "regional_domain_name": {
        "type": "string",
        "description_kind": "plain",
        "computed": true
      },
      "regional_zone_id": {
        "type": "string",
        "description_kind": "plain",
        "computed": true
      },
      "security_policy": {
        "type": "string",
        "description_kind": "plain",
        "computed": true
      },
      "tags": {
        "type": [
          "map",
          "string"
        ],
        "description_kind": "plain",
        "optional": true,
        "computed": true
      }
    },
    "description_kind": "plain"
  }
}