{
  "version": 0,
  "block": {
    "attributes": {
      "acl": {
        "type": [
          "set",
          [
            "object",
            {
              "access_policy": [
                "list",
                [
                  "object",
                  {
                    "expiry": "string",
                    "permissions": "string",
                    "start": "string"
                  }
                ]
              ],
              "id": "string"
            }
          ]
        ],
        "description_kind": "plain",
        "computed": true
      },
      "id": {
        "type": "string",
        "description_kind": "plain",
        "computed": true
      },
      "name": {
        "type": "string",
        "description_kind": "plain",
        "required": true
      },
      "resource_manager_id": {
        "type": "string",
        "description_kind": "plain",
        "computed": true
      },
      "storage_account_name": {
        "type": "string",
        "description_kind": "plain",
        "required": true
      }
    },
    "block_types": {
      "timeouts": {
        "nesting_mode": "single",
        "block": {
          "attributes": {
            "read": {
              "type": "string",
              "description_kind": "plain",
              "optional": true
            }
          },
          "description_kind": "plain"
        }
      }
    },
    "description_kind": "plain"
  }
}