{
  "version": 0,
  "block": {
    "attributes": {
      "aws_account_id": {
        "type": "string",
        "description_kind": "plain",
        "optional": true,
        "computed": true
      },
      "aws_account_region": {
        "type": "string",
        "description_kind": "plain",
        "required": true
      },
      "created_at": {
        "type": "string",
        "description_kind": "plain",
        "computed": true
      },
      "created_by": {
        "type": "string",
        "description_kind": "plain",
        "computed": true
      },
      "description": {
        "type": "string",
        "description_kind": "plain",
        "optional": true,
        "computed": true
      },
      "domain_identifier": {
        "type": "string",
        "description_kind": "plain",
        "required": true
      },
      "environment_blueprint_identifier": {
        "type": "string",
        "description_kind": "plain",
        "required": true
      },
      "id": {
        "type": "string",
        "description_kind": "plain",
        "computed": true
      },
      "name": {
        "type": "string",
        "description_kind": "plain",
        "required": true
      },
      "project_identifier": {
        "type": "string",
        "description_kind": "plain",
        "required": true
      },
      "region": {
        "type": "string",
        "description": "Region where this resource will be [managed](https://docs.aws.amazon.com/general/latest/gr/rande.html#regional-endpoints). Defaults to the Region set in the [provider configuration](https://registry.terraform.io/providers/hashicorp/aws/latest/docs#aws-configuration-reference).",
        "description_kind": "plain",
        "optional": true,
        "computed": true
      },
      "updated_at": {
        "type": "string",
        "description_kind": "plain",
        "computed": true
      }
    },
    "block_types": {
      "user_parameters": {
        "nesting_mode": "list",
        "block": {
          "attributes": {
            "name": {
              "type": "string",
              "description_kind": "plain",
              "optional": true
            },
            "value": {
              "type": "string",
              "description_kind": "plain",
              "optional": true
            }
          },
          "description_kind": "plain"
        }
      }
    },
    "description_kind": "plain"
  }
}